{
  "fill" : "automatic",
  "groups" : [
    {
      "layers" : [
        {
          "glass-specializations" : [
            {
              "value" : true
            },
            {
              "appearance" : "light",
              "value" : true
            },
            {
              "appearance" : "dark",
              "value" : true
            },
            {
              "appearance" : "tinted",
              "value" : true
            }
          ],
          "image-name" : "Bildebene 2.png",
          "name" : "Bildebene 2",
          "position" : {
            "scale" : 1,
            "translation-in-points" : [
              0,
              0
            ]
          }
        }
      ],
      "shadow" : {
        "kind" : "neutral",
        "opacity" : 0.5
      },
      "translucency" : {
        "enabled" : true,
        "value" : 0.5
      }
    }
  ],
  "supported-platforms" : {
    "squares" : [
      "macOS"
    ]
  }
}